sat/__init__.py
sat/db.py
sat/gravity_forms.py
sat/logs.py
sat/prtg.py
sat/slack.py
sat/models/__init__.py
sat/models/ccure/__init__.py
sat/models/ccure/access.py
sat/models/ccure/assets.py
sat/models/ccure/types.py
sat_utils-1.7.5.dist-info/LICENSE
sat_utils-1.7.5.dist-info/WHEEL
sat_utils-1.7.5.dist-info/METADATA
sat_utils-1.7.5.dist-info/RECORD
