Metadata-Version: 2.1
Name: sat-utils
Version: 1.7.5
Summary: Contains a collection of shared utility functions
Author-email: Ryan Semmler <rsemmle@ncsu.edu>, Shawn Taylor <staylor8@ncsu.edu>, Jeremy Gibson <jmgibso3@ncsu.edu>, John Champion <jtchampi@ncsu.edu>
Requires-Python: >=3.9
Requires-Dist: slack-sdk==3.27.1
Requires-Dist: requests==2.31.0
Requires-Dist: cx_Oracle==8.3.0
Requires-Dist: oracledb==2.0.1
Requires-Dist: pyodbc==5.1.0
Requires-Dist: requests_oauthlib==1.3.1
Requires-Dist: pydantic==2.6.4
Requires-Dist: pydantic[email]==2.6.4
Requires-Dist: pytest>=6.2.5, <7.0.0 ; extra == "dev"
Requires-Dist: pytest-mock>=3.10.0, <4.0.0 ; extra == "dev"
Requires-Dist: pytest-cov>=4.0.0, <5.0.0 ; extra == "dev"
Requires-Dist: coverage[toml]>=6.2 ; extra == "dev"
Requires-Dist: black>=23.3.0, <24.0.0 ; extra == "dev"
Requires-Dist: mypy>=1.2.0, <2.0.0 ; extra == "dev"
Requires-Dist: ruff==0.0.263 ; extra == "dev"
Requires-Dist: mkdocs-material>=9.1.6, <10.0.0 ; extra == "dev"
Requires-Dist: Pygments>=2.10.0, <3.0.0 ; extra == "dev"
Requires-Dist: bandit>=1.7.4, <2.0.0 ; extra == "dev"
Requires-Dist: pre-commit>=2.16.0, <3.0.0 ; extra == "dev"
Requires-Dist: isort>=5.10.1, <6.0.0 ; extra == "dev"
Requires-Dist: pyupgrade>=2.29.1, <3.0.0 ; extra == "dev"
Requires-Dist: jupyterlab>=3.2.0, <4.0.0 ; extra == "dev"
Requires-Dist: flit>=3.8.0, <4.0.0 ; extra == "dev"
Project-URL: Homepage, https://github.com/ncstate-sat/sat-utils
Provides-Extra: dev
